{
    "update_id": 356024183,
    "callback_query": {
        "id": "242028631530992939",
        "from": {
            "id": 56351682,
            "is_bot": false,
            "first_name": "Oren",
            "last_name": "Griffin",
            "language_code": "en-IL"
        },
        "message": {
            "message_id": 103,
            "from": {
                "id": 583968863,
                "is_bot": true,
                "first_name": "happyBot",
                "username": "happyDoingBot"
            },
            "chat": {
                "id": 184823763,
                "first_name": "Oren",
                "last_name": "Griffin",
                "type": "private"
            },
            "date": 1539582258,
            "text": "some text"
        },
        "chat_instance": "2087159535196798780",
        "data": "/report"
    }
}
